COPYING
COPYING.LESSER
MANIFEST.in
README.rst
setup.cfg
setup.py
ORTHPOLxx/AUTHORS
ORTHPOLxx/COPYING
ORTHPOLxx/COPYING.LESSER
ORTHPOLxx/ChangeLog
ORTHPOLxx/INSTALL
ORTHPOLxx/Makefile
ORTHPOLxx/Makefile.am
ORTHPOLxx/Makefile.in
ORTHPOLxx/NEWS
ORTHPOLxx/ORTHPOL
ORTHPOLxx/README
ORTHPOLxx/acconfig.h
ORTHPOLxx/aclocal.m4
ORTHPOLxx/config.guess
ORTHPOLxx/config.h
ORTHPOLxx/config.h.in
ORTHPOLxx/config.log
ORTHPOLxx/config.status
ORTHPOLxx/config.sub
ORTHPOLxx/configure
ORTHPOLxx/configure.ac
ORTHPOLxx/depcomp
ORTHPOLxx/install-sh
ORTHPOLxx/liborthpol-1.0.la
ORTHPOLxx/liborthpol-1.0.pc
ORTHPOLxx/liborthpol-1.0.pc.in
ORTHPOLxx/libtool
ORTHPOLxx/ltmain.sh
ORTHPOLxx/missing
ORTHPOLxx/stamp-h1
ORTHPOLxx/.libs/liborthpol-1.0.a
ORTHPOLxx/.libs/liborthpol-1.0.la
ORTHPOLxx/.libs/liborthpol-1.0.lai
ORTHPOLxx/.libs/liborthpol-1.0.so.1
ORTHPOLxx/.libs/liborthpol-1.0.so.1.0.0
ORTHPOLxx/autom4te.cache/output.0
ORTHPOLxx/autom4te.cache/output.1
ORTHPOLxx/autom4te.cache/requests
ORTHPOLxx/autom4te.cache/traces.0
ORTHPOLxx/autom4te.cache/traces.1
ORTHPOLxx/build/include/liborthpol-1.0/ORTHPOLxx/ORTHPOLPP.hpp
ORTHPOLxx/build/include/liborthpol-1.0/ORTHPOLxx/f77char.h
ORTHPOLxx/build/include/liborthpol-1.0/ORTHPOLxx/f77cmplx.h
ORTHPOLxx/build/include/liborthpol-1.0/ORTHPOLxx/f77matrix.h
ORTHPOLxx/build/include/liborthpol-1.0/ORTHPOLxx/fortran.h
ORTHPOLxx/build/lib/liborthpol-1.0.la
ORTHPOLxx/build/lib/liborthpol-1.0.so.1
ORTHPOLxx/build/lib/liborthpol-1.0.so.1.0.0
ORTHPOLxx/build/lib/liborthpol-1.0/include/config.h
ORTHPOLxx/build/lib/pkgconfig/liborthpol-1.0.pc
ORTHPOLxx/src/.dirstamp
ORTHPOLxx/src/ORTHPOLPP.cpp
ORTHPOLxx/src/ORTHPOLPP.hpp
ORTHPOLxx/src/autoscan.log
ORTHPOLxx/src/cheb.f
ORTHPOLxx/src/chri.f
ORTHPOLxx/src/configure.scan
ORTHPOLxx/src/d1mach.f
ORTHPOLxx/src/dcheb.f
ORTHPOLxx/src/dchri.f
ORTHPOLxx/src/dgauss.f
ORTHPOLxx/src/dgchri.f
ORTHPOLxx/src/dkern.f
ORTHPOLxx/src/dknum.f
ORTHPOLxx/src/dlancz.f
ORTHPOLxx/src/dlob.f
ORTHPOLxx/src/dmcdis.f
ORTHPOLxx/src/dmcheb.f
orthpol.egg-info/PKG-INFO
orthpol.egg-info/SOURCES.txt
orthpol.egg-info/dependency_links.txt
orthpol.egg-info/not-zip-safe
orthpol.egg-info/top_level.txt
