Metadata-Version: 1.0
Name: orthpol
Version: 0.2.19
Summary: Python wrapper for the ORTHPOL package
Home-page: http://www2.compute.dtu.dk/~dabi/
Author: Daniele Bigoni
Author-email: dabi@dtu.dk
License: COPYING.LESSER
Platform: UNKNOWN
